motliere/__init__.py
motliere/motliere.py
motliere/data/fra.derivations
motliere/data/fra.segmentations
motliere-1.1.8.2.dist-info/LICENSE
motliere-1.1.8.2.dist-info/METADATA
motliere-1.1.8.2.dist-info/WHEEL
motliere-1.1.8.2.dist-info/top_level.txt
motliere-1.1.8.2.dist-info/RECORD
