Metadata-Version: 2.1
Name: motliere
Version: 1.1.8.2
Summary: A morphological and linguistically motivated segmentation tool for French !
Home-page: https://github.com/MorphSeg/Motliere/
Author: Nicolas, Rémi
Author-email: E239002K@etu.univ-nantes.fr, E23B509C@etu.univ-nantes.fr
License: GPLv3
Classifier: License :: OSI Approved :: GNU General Public License v3 (GPLv3)
Classifier: Programming Language :: Python :: 3
License-File: LICENSE
Requires-Dist: numpy <2.0.0
Requires-Dist: pandas
Requires-Dist: spacy
